reloreta/__init__.py
reloreta/core.py
reloreta-0.0.1.dist-info/LICENSE.txt
reloreta-0.0.1.dist-info/METADATA
reloreta-0.0.1.dist-info/WHEEL
reloreta-0.0.1.dist-info/top_level.txt
reloreta-0.0.1.dist-info/RECORD
